powerschool_adapter/__init__.py
powerschool_adapter/operator.py
powerschool_adapter/paginator.py
powerschool_adapter/powerschool.py
powerschool_adapter/request.py
powerschool_adapter/response.py
powerschool_adapter-1.0.3.dist-info/METADATA
powerschool_adapter-1.0.3.dist-info/WHEEL
powerschool_adapter-1.0.3.dist-info/licenses/LICENSE
powerschool_adapter-1.0.3.dist-info/RECORD
