Metadata-Version: 2.4
Name: powerschool-adapter
Version: 1.0.3
Summary: A Python adapter for PowerSchool API integration
Project-URL: Homepage, https://github.com/tonylabs/python-powerschool-adapter
Project-URL: Repository, https://github.com/tonylabs/python-powerschool-adapter.git
Project-URL: Bug Tracker, https://github.com/tonylabs/python-powerschool-adapter/issues
Author-email: "TONYLABS TECH CO., LTD." <tony.wang@tonylabs.com>
License: MIT
License-File: LICENSE
Keywords: adapter,api,education,powerschool
Classifier: Development Status :: 3 - Alpha
Classifier: Intended Audience :: Education
Classifier: License :: OSI Approved :: MIT License
Classifier: Programming Language :: Python :: 3
Classifier: Programming Language :: Python :: 3.7
Classifier: Programming Language :: Python :: 3.8
Classifier: Programming Language :: Python :: 3.9
Classifier: Programming Language :: Python :: 3.10
Classifier: Topic :: Education
Requires-Python: >=3.7
Requires-Dist: diskcache>=5.6.0
Requires-Dist: requests>=2.20.0
Provides-Extra: dev
Requires-Dist: faker>=33.3.1; extra == 'dev'
Requires-Dist: python-dotenv>=1.0.1; extra == 'dev'
